qazxswTest/test1.py
qazxswTest/test2.py
qazxswTest-0.0.0.2.dist-info/METADATA
qazxswTest-0.0.0.2.dist-info/WHEEL
qazxswTest-0.0.0.2.dist-info/top_level.txt
qazxswTest-0.0.0.2.dist-info/RECORD
